{"resultaat": "Aangenomen.", "onderwerp": "Moties ingediend bij Vaststelling van de begrotingsstaten van het Ministerie van Sociale Zaken en Werkgelegenheid (XV) voor het jaar 2023", "besluit_id": "a557d158-89c8-4328-92cb-b74156d43378", "datum": "2022-12-06 16:34:40", "stemgedrag": {"Forum voor Democratie": "Voor", "Groep Van Haga": "Voor", "ChristenUnie": "Voor", "Partij voor de Vrijheid": "Voor", "BIJ1": "Voor", "BBB": "Voor", "DENK": "Voor", "Fractie Den Haan": "Voor", "GroenLinks": "Tegen", "Volt": "Voor", "G\u00fcndo\u011fan": "Voor", "Volkspartij voor Vrijheid en Democratie": "Voor", "Partij van de Arbeid": "Tegen", "JA21": "Voor", "Democraten 66": "Voor", "Socialistische Partij": "Tegen", "Partij voor de Dieren": "Tegen", "Christen-Democratisch App\u00e8l": "Voor", "Staatkundig Gereformeerde Partij": "Voor", "Omtzigt": "Voor"}}