{"resultaat": "Aangenomen.", "onderwerp": "Overige moties ingediend bij het debat over sms-berichten op de telefoon van de minister-president", "besluit_id": "5f15409b-918f-4614-83ef-d5358b8eb691", "datum": "2022-05-24 15:59:12", "stemgedrag": {"Partij van de Arbeid": "Tegen", "Staatkundig Gereformeerde Partij": "Tegen", "Democraten 66": "Tegen", "Omtzigt": "Niet deelgenomen", "DENK": "Voor", "Groep Van Haga": "Voor", "G\u00fcndo\u011fan": "Niet deelgenomen", "BIJ1": "Tegen", "ChristenUnie": "Voor", "Partij voor de Vrijheid": "Voor", "Socialistische Partij": "Voor", "Fractie Den Haan": "Voor", "JA21": "Voor", "GroenLinks": "Tegen", "Christen-Democratisch App\u00e8l": "Tegen", "Partij voor de Dieren": "Voor", "Volt": "Tegen", "BBB": "Voor", "Volkspartij voor Vrijheid en Democratie": "Voor", "Forum voor Democratie": "Voor"}}