{"resultaat": "Aangenomen.", "onderwerp": "Moties ingediend bij het tweeminutendebat Toerisme", "besluit_id": "5c02d251-04b7-4b9b-a611-6d5942be4652", "datum": "2022-06-07 16:13:07", "stemgedrag": {"Democraten 66": "Voor", "Partij van de Arbeid": "Voor", "Partij voor de Vrijheid": "Tegen", "JA21": "Voor", "Volt": "Voor", "Socialistische Partij": "Voor", "ChristenUnie": "Voor", "Christen-Democratisch App\u00e8l": "Voor", "Volkspartij voor Vrijheid en Democratie": "Voor", "Fractie Den Haan": "Voor", "Staatkundig Gereformeerde Partij": "Voor", "Forum voor Democratie": "Voor", "GroenLinks": "Voor", "DENK": "Voor", "BBB": "Voor", "Omtzigt": "Voor", "BIJ1": "Voor", "Groep Van Haga": "Voor", "Partij voor de Dieren": "Voor", "G\u00fcndo\u011fan": "Voor"}}