{"resultaat": "Aangenomen.", "onderwerp": "aangehouden motie ingediend bij de initiatiefnota van het lid Van der Werf over \u201cLet\u2019s talk about seksueel geweld\u201d", "besluit_id": "7c55c3cc-4c52-4013-86e0-83137e1d2470", "datum": "2023-05-30 16:26:36", "stemgedrag": {"Democraten 66": "Voor", "Volt": "Voor", "Partij voor de Vrijheid": "Voor", "Partij voor de Dieren": "Voor", "G\u00fcndo\u011fan": "Voor", "BIJ1": "Voor", "DENK": "Voor", "ChristenUnie": "Voor", "Staatkundig Gereformeerde Partij": "Voor", "Omtzigt": "Niet deelgenomen", "JA21": "Voor", "BBB": "Voor", "Groep Van Haga": "Voor", "Forum voor Democratie": "Tegen", "GroenLinks": "Voor", "Volkspartij voor Vrijheid en Democratie": "Voor", "Christen-Democratisch App\u00e8l": "Voor", "Fractie Den Haan": "Voor", "Partij van de Arbeid": "Voor", "Socialistische Partij": "Voor"}}