{"resultaat": "Verworpen.", "onderwerp": "Moties ingediend bij het tweeminutendebat Woningbouwopgave en koopsector", "besluit_id": "5502fe14-20fe-4d0f-ac40-8b5b455c740f", "datum": "2023-09-26 16:30:53", "stemgedrag": {"Partij voor de Vrijheid": "Voor", "BIJ1": "Voor", "G\u00fcndo\u011fan": "Niet deelgenomen", "Forum voor Democratie": "Tegen", "Omtzigt": "Voor", "BBB": "Voor", "Fractie Den Haan": "Voor", "DENK": "Voor", "JA21": "Tegen", "Staatkundig Gereformeerde Partij": "Voor", "Groep Van Haga": "Tegen", "Socialistische Partij": "Voor", "Christen-Democratisch App\u00e8l": "Tegen", "GroenLinks": "Voor", "Ephraim": "Tegen", "Partij voor de Dieren": "Voor", "Partij van de Arbeid": "Voor", "Democraten 66": "Tegen", "Volt": "Voor", "Volkspartij voor Vrijheid en Democratie": "Tegen", "ChristenUnie": "Voor"}}