{"resultaat": "Verworpen.", "onderwerp": "Moties ingediend bij het tweeminutendebat Brandbrief ALS pati\u00ebntenvereniging m.b.t. moties over geneesmiddelenbeleid ALS-pati\u00ebnten", "besluit_id": "850b664e-6483-44e2-9065-cc149934c28c", "datum": "2023-09-26 16:30:53", "stemgedrag": {"Forum voor Democratie": "Voor", "Staatkundig Gereformeerde Partij": "Voor", "Christen-Democratisch App\u00e8l": "Tegen", "JA21": "Tegen", "DENK": "Voor", "BBB": "Voor", "Volt": "Tegen", "BIJ1": "Voor", "GroenLinks": "Tegen", "Volkspartij voor Vrijheid en Democratie": "Tegen", "Partij voor de Dieren": "Tegen", "Socialistische Partij": "Tegen", "Groep Van Haga": "Voor", "Omtzigt": "Tegen", "Democraten 66": "Tegen", "Partij van de Arbeid": "Tegen", "G\u00fcndo\u011fan": "Niet deelgenomen", "Fractie Den Haan": "Voor", "ChristenUnie": "Tegen", "Partij voor de Vrijheid": "Voor", "Ephraim": "Voor"}}