{"resultaat": "Verworpen.", "onderwerp": "Moties ingediend bij het tweeminutendebat Niet informeren van de Kamer over de beschikbaarheid van opnames van OMT-vergaderingen", "besluit_id": "7be2f3d7-fca9-40d7-aa38-50f505a5e8d0", "datum": "2023-03-28 16:25:39", "stemgedrag": {"Partij voor de Dieren": "Voor", "Omtzigt": "Voor", "Forum voor Democratie": "Voor", "Volt": "Tegen", "Partij voor de Vrijheid": "Voor", "Groep Van Haga": "Voor", "GroenLinks": "Tegen", "G\u00fcndo\u011fan": "Tegen", "DENK": "Voor", "Partij van de Arbeid": "Tegen", "ChristenUnie": "Tegen", "Staatkundig Gereformeerde Partij": "Voor", "BIJ1": "Voor", "Democraten 66": "Tegen", "Fractie Den Haan": "Tegen", "Christen-Democratisch App\u00e8l": "Tegen", "BBB": "Voor", "Socialistische Partij": "Voor", "JA21": "Voor", "Volkspartij voor Vrijheid en Democratie": "Tegen"}}